{"commitInfo":{"timestamp":1747279803844,"operation":"WRITE","operationParameters":{"mode":"Append","partitionBy":"[\"date_partition\"]"},"readVersion":6,"isolationLevel":"Serializable","isBlindAppend":true,"operationMetrics":{"numFiles":"5","numOutputRows":"5","numOutputBytes":"2390"},"engineInfo":"Apache-Spark/3.5.5 Delta-Lake/3.3.1","txnId":"3ae78bd6-b6ea-4424-a0d6-cb0724eecc1a"}}
{"add":{"path":"date_partition=2025-05-15/part-00001-1b307fb0-15fe-470a-b931-fe87a6dc2ea8.c000.snappy.parquet","partitionValues":{"date_partition":"2025-05-15"},"size":478,"modificationTime":1747279803765,"dataChange":true,"stats":"{\"numRecords\":1,\"minValues\":{\"id\":0},\"maxValues\":{\"id\":0},\"nullCount\":{\"id\":0}}"}}
{"add":{"path":"date_partition=2025-05-15/part-00003-e15b2775-33eb-4351-9861-1b601516be11.c000.snappy.parquet","partitionValues":{"date_partition":"2025-05-15"},"size":478,"modificationTime":1747279803765,"dataChange":true,"stats":"{\"numRecords\":1,\"minValues\":{\"id\":1},\"maxValues\":{\"id\":1},\"nullCount\":{\"id\":0}}"}}
{"add":{"path":"date_partition=2025-05-15/part-00004-068cfdbd-da6a-4ab4-88f0-3d6eea6e6af7.c000.snappy.parquet","partitionValues":{"date_partition":"2025-05-15"},"size":478,"modificationTime":1747279803765,"dataChange":true,"stats":"{\"numRecords\":1,\"minValues\":{\"id\":2},\"maxValues\":{\"id\":2},\"nullCount\":{\"id\":0}}"}}
{"add":{"path":"date_partition=2025-05-15/part-00006-5c521054-ed31-4f70-aa7e-79a2f7815656.c000.snappy.parquet","partitionValues":{"date_partition":"2025-05-15"},"size":478,"modificationTime":1747279803765,"dataChange":true,"stats":"{\"numRecords\":1,\"minValues\":{\"id\":3},\"maxValues\":{\"id\":3},\"nullCount\":{\"id\":0}}"}}
{"add":{"path":"date_partition=2025-05-15/part-00007-96d50a74-e232-4f51-97a7-2a3976b4b68c.c000.snappy.parquet","partitionValues":{"date_partition":"2025-05-15"},"size":478,"modificationTime":1747279803765,"dataChange":true,"stats":"{\"numRecords\":1,\"minValues\":{\"id\":4},\"maxValues\":{\"id\":4},\"nullCount\":{\"id\":0}}"}}
